{
  "orders": [
    {
      "nbJours": 1,
      "tva": 20,
      "state": "Option",
      "tjmHt": 1200,
      "typePresta": "coaching",
      "client": "Capgemini",
      "comment": "merci cap",
      "id": 2
    },
    {
      "nbJours": 1,
      "tva": 20,
      "state": "Confirmed",
      "tjmHt": 1200,
      "typePresta": "formation",
      "client": "Edugroupe",
      "comment": "merci edugroupe",
      "id": 3
    }
  ],
  "clients": [
    {
      "name": "Christophe",
      "ca": 12000,
      "state": "Inactive",
      "id": 1
    },
    {
      "name": "Jeff",
      "ca": 22000,
      "state": "Active",
      "id": 2
    }
  ]
}